hay_say_common/__init__.py
hay_say_common/cache.py
hay_say_common/file_integration.py
hay_say_common/server_utility.py
hay_say_common/utility.py
hay_say_common-1.0.8.dist-info/LICENSE
hay_say_common-1.0.8.dist-info/METADATA
hay_say_common-1.0.8.dist-info/WHEEL
hay_say_common-1.0.8.dist-info/top_level.txt
hay_say_common-1.0.8.dist-info/RECORD
